Metadata-Version: 2.1
Name: MiniFortniteAPI
Version: 1.0.0
Summary: Easy to use MiniFortniteAPI module.
Home-page: 
Author: faktorr
Author-email: patryktarasiuk04@gmail.com
License: MIT
Keywords: MiniFortniteAPI
Classifier: License :: OSI Approved :: MIT License
Classifier: Intended Audience :: Developers
Classifier: Operating System :: OS Independent
Classifier: Programming Language :: Python :: 3.5
Classifier: Programming Language :: Python :: 3.6
Classifier: Programming Language :: Python :: 3.7
Classifier: Programming Language :: Python :: 3.8
Classifier: Programming Language :: Python :: 3.9
License-File: LICENSE.txt
